sepa_netherlands
tests
