Metadata-Version: 1.0
Name: sepa-netherlands
Version: 0.2.5
Summary: Python library which handles communication with Dutch banks for processing SEPA eMandates.
Home-page: https://github.com/VerenigingCampusKabel/python-sepa-netherlands
Author: Vereniging Campus Kabel
Author-email: info@vck.utwente.nl
License: The MIT License (MIT)
